{
	"credit": "Made with Blockbench",
	"ambientocclusion": false,
	"texture_size": [32, 32],
	"textures": {
		"particle": "rpgworldmod:block/paralily",
		"crop": "rpgworldmod:block/paralily"
	},
	"elements": [
		{
			"from": [6, -3.25, 0],
			"to": [6, 12.75, 16],
			"shade": false,
			"rotation": {"angle": 22.5, "axis": "z", "origin": [0, -1, 0]},
			"faces": {
				"east": {"uv": [0, 0, 8, 8], "texture": "#crop"},
				"west": {"uv": [0, 0, 8, 8], "texture": "#crop"}
			}
		},
		{
			"from": [9, 3, 0],
			"to": [9, 19, 16],
			"shade": false,
			"rotation": {"angle": -22.5, "axis": "z", "origin": [0, -1, 0]},
			"faces": {
				"east": {"uv": [0, 0, 8, 8], "texture": "#crop"},
				"west": {"uv": [0, 0, 8, 8], "texture": "#crop"}
			}
		},
		{
			"from": [0, -3.25, 6],
			"to": [16, 12.75, 6],
			"shade": false,
			"rotation": {"angle": -22.5, "axis": "x", "origin": [0, -1, 0]},
			"faces": {
				"north": {"uv": [0, 0, 8, 8], "texture": "#crop"},
				"south": {"uv": [0, 0, 8, 8], "texture": "#crop"}
			}
		},
		{
			"from": [0, 3, 9],
			"to": [16, 19, 9],
			"shade": false,
			"rotation": {"angle": 22.5, "axis": "x", "origin": [0, -1, 0]},
			"faces": {
				"north": {"uv": [0, 0, 8, 8], "texture": "#crop"},
				"south": {"uv": [0, 0, 8, 8], "texture": "#crop"}
			}
		},
		{
			"from": [0, 0, 0],
			"to": [16, 0, 16],
			"faces": {
				"north": {"uv": [0, 0, 16, 0], "texture": "#missing"},
				"east": {"uv": [0, 0, 16, 0], "texture": "#missing"},
				"south": {"uv": [0, 0, 16, 0], "texture": "#missing"},
				"west": {"uv": [0, 0, 16, 0], "texture": "#missing"},
				"up": {"uv": [8, 0, 16, 8], "texture": "#crop", "tintindex": 0},
				"down": {"uv": [16, 0, 8, 8], "texture": "#crop", "tintindex": 0}
			}
		}
	]
}